{"commitInfo":{"timestamp":1735077727655,"operation":"WRITE","operationParameters":{"mode":"ErrorIfExists","partitionBy":"[]"},"isolationLevel":"Serializable","isBlindAppend":true,"operationMetrics":{"numFiles":"4","numOutputRows":"3","numOutputBytes":"2571"},"engineInfo":"Apache-Spark/3.5.3 Delta-Lake/3.2.1","txnId":"ba222ff4-9905-4b10-a06c-5067f36a7f98"}}
{"metaData":{"id":"fcce2630-64f4-49cf-b3c4-96d21ed65a66","format":{"provider":"parquet","options":{}},"schemaString":"{\"type\":\"struct\",\"fields\":[{\"name\":\"age\",\"type\":\"long\",\"nullable\":true,\"metadata\":{}},{\"name\":\"first_name\",\"type\":\"string\",\"nullable\":true,\"metadata\":{}}]}","partitionColumns":[],"configuration":{},"createdTime":1735077727393}}
{"protocol":{"minReaderVersion":1,"minWriterVersion":2}}
{"add":{"path":"part-00002-468cf97f-1015-4265-ab5a-8a501aae6036-c000.snappy.parquet","partitionValues":{},"size":726,"modificationTime":1735077727622,"dataChange":true,"stats":"{\"numRecords\":1,\"minValues\":{\"age\":47,\"first_name\":\"bob\"},\"maxValues\":{\"age\":47,\"first_name\":\"bob\"},\"nullCount\":{\"age\":0,\"first_name\":0}}"}}
{"add":{"path":"part-00005-5d9ec1fc-98f4-4e73-b338-1212170c6bdb-c000.snappy.parquet","partitionValues":{},"size":719,"modificationTime":1735077727644,"dataChange":true,"stats":"{\"numRecords\":1,\"minValues\":{\"age\":23,\"first_name\":\"li\"},\"maxValues\":{\"age\":23,\"first_name\":\"li\"},\"nullCount\":{\"age\":0,\"first_name\":0}}"}}
{"add":{"path":"part-00007-4ed9bc3c-8512-4348-b052-f50e4b71c9f5-c000.snappy.parquet","partitionValues":{},"size":733,"modificationTime":1735077727644,"dataChange":true,"stats":"{\"numRecords\":1,\"minValues\":{\"age\":51,\"first_name\":\"leah\"},\"maxValues\":{\"age\":51,\"first_name\":\"leah\"},\"nullCount\":{\"age\":0,\"first_name\":0}}"}}
